leaf_properties/__init__.py
leaf_properties/leaf_properties/__init__.py
leaf_properties/leaf_properties/leaf_angle.py
leaf_properties/leaf_properties/leaf_area.py
leaf_properties/leaf_properties/leaf_geometry.py
leaf_properties/utility/__init__.py
leaf_properties/utility/angles.py
leaf_properties/utility/area.py
leaf_properties/utility/clustering.py
leaf_properties/utility/distance.py
leaf_properties/utility/filters.py
leaf_properties/utility/nnsearch.py
leaf_properties/utility/normals.py
leaf_properties/utility/point_utils.py
leaf_properties/utility/smoothing.py
leaf_properties-0.2.4.dist-info/LICENSE
leaf_properties-0.2.4.dist-info/METADATA
leaf_properties-0.2.4.dist-info/WHEEL
leaf_properties-0.2.4.dist-info/top_level.txt
leaf_properties-0.2.4.dist-info/RECORD
