Metadata-Version: 2.1
Name: leaf-properties
Version: 0.2.4
Summary: Retrieves leaf properties estimates from leaf-only LiDAR data.
Home-page: UNKNOWN
Author: Matheus Boni Vicari
Author-email: matheus.boni.vicari@gmail.com
License: LICENSE.txt
Keywords: wood/leaf separation TLS point cloud LiDAR
Platform: UNKNOWN
Classifier: Programming Language :: Python
Classifier: Topic :: Scientific/Engineering
Requires-Dist: numba
Requires-Dist: numpy (>=1.13)
Requires-Dist: pandas (>=0.19)
Requires-Dist: scikit-learn (>=0.20.1)
Requires-Dist: scipy (>=1.2.0)
